rio_hist/__init__.py
rio_hist/match.py
rio_hist/plot.py
rio_hist/utils.py
rio_hist/scripts/__init__.py
rio_hist/scripts/cli.py
rio_hist-1.0.0.dist-info/METADATA
rio_hist-1.0.0.dist-info/WHEEL
rio_hist-1.0.0.dist-info/entry_points.txt
rio_hist-1.0.0.dist-info/top_level.txt
rio_hist-1.0.0.dist-info/RECORD
