Metadata-Version: 2.1
Name: rio-hist
Version: 1.0.0
Summary: Histogram matching plugin for rasterio
Home-page: https://github.com/mapbox/rio-hist
Author: Matthew Perry
Author-email: perry@mapbox.com
License: BSD
Platform: UNKNOWN
Requires-Dist: click
Requires-Dist: rasterio (~=1.0)
Requires-Dist: rio-color (>=0.4)
Provides-Extra: plot
Requires-Dist: matplotlib ; extra == 'plot'
Provides-Extra: test
Requires-Dist: pytest ; extra == 'test'
Requires-Dist: pytest-cov ; extra == 'test'
Requires-Dist: codecov ; extra == 'test'
